__init__.py
gymnasium/__init__.py
gymnasium/pick_high/PickHigh.py
gymnasium/pick_high/__init__.py
gymnasium/pick_low/PickLow.py
gymnasium/pick_low/__init__.py
gymnasium/shuffler/Shuffler.py
gymnasium/shuffler/__init__.py
rl_enviros_rlate-0.0.4.dist-info/LICENSE
rl_enviros_rlate-0.0.4.dist-info/METADATA
rl_enviros_rlate-0.0.4.dist-info/WHEEL
rl_enviros_rlate-0.0.4.dist-info/top_level.txt
rl_enviros_rlate-0.0.4.dist-info/RECORD
